home/bbeltr1/.local/share/pip-cache/all-packages.txt
pip_cache/__init__.py
pip_cache/xdg.py
pip_cache/externals/__init__.py
pip_cache/externals/six.py
pip_cache-0.0.6.dist-info/DESCRIPTION.rst
pip_cache-0.0.6.dist-info/METADATA
pip_cache-0.0.6.dist-info/RECORD
pip_cache-0.0.6.dist-info/WHEEL
pip_cache-0.0.6.dist-info/entry_points.txt
pip_cache-0.0.6.dist-info/metadata.json
pip_cache-0.0.6.dist-info/top_level.txt
