Metadata-Version: 2.0
Name: pip-cache
Version: 0.0.6
Summary: Local PyPi Package Name Cache
Home-page: https://github.com/brunobeltran/pip-cache
Author: Bruno Beltran
Author-email: brunobeltran0@gmail.com
License: MIT
Keywords: bash completion pip pypi
Platform: UNKNOWN
Classifier: Development Status :: 3 - Alpha
Classifier: Intended Audience :: Developers
Classifier: License :: OSI Approved :: MIT License
Classifier: Programming Language :: Python :: 2
Classifier: Programming Language :: Python :: 2.6
Classifier: Programming Language :: Python :: 2.7
Classifier: Programming Language :: Python :: 3
Classifier: Programming Language :: Python :: 3.2
Classifier: Programming Language :: Python :: 3.3
Classifier: Programming Language :: Python :: 3.4
Classifier: Environment :: Console
Classifier: Topic :: Utilities
Provides-Extra: test
Requires-Dist: pytest; extra == 'test'
